py_vreport/__init__.py
py_vreport/cli.py
py_vreport/formatters.py
py_vreport/models.py
py_vreport/parser.py
py_vreport/py.typed
py_vreport-0.2.0.dist-info/METADATA
py_vreport-0.2.0.dist-info/WHEEL
py_vreport-0.2.0.dist-info/entry_points.txt
py_vreport-0.2.0.dist-info/RECORD
