Metadata-Version: 2.4
Name: py-vreport
Version: 0.2.0
Summary: A modern Python parser and CLI tool for Vector CANoe XML test reports with rich terminal output
Project-URL: Homepage, https://github.com/MohamedHamed19m/py_vreport
Project-URL: Repository, https://github.com/MohamedHamed19m/py_vreport
Project-URL: Bug Tracker, https://github.com/MohamedHamed19m/py_vreport/issues
Project-URL: Documentation, https://github.com/MohamedHamed19m/py_vreport#readme
Project-URL: Changelog, https://github.com/MohamedHamed19m/py_vreport/releases
Project-URL: Source Code, https://github.com/MohamedHamed19m/py_vreport
Author-email: MohamedHamed19m <mohamedahamed1915@gmail.com>
Maintainer-email: MohamedHamed19m <mohamedahamed1915@gmail.com>
License: MIT
Keywords: automotive,can,canoe,cli,diagnostic,ecu,parser,test-analysis,test-automation,test-report,test-results,testing,uds,vector,vector-canoe,xml
Classifier: Development Status :: 4 - Beta
Classifier: Environment :: Console
Classifier: Intended Audience :: Developers
Classifier: Intended Audience :: Manufacturing
Classifier: Intended Audience :: Science/Research
Classifier: License :: OSI Approved :: MIT License
Classifier: Operating System :: MacOS
Classifier: Operating System :: Microsoft :: Windows
Classifier: Operating System :: OS Independent
Classifier: Operating System :: POSIX :: Linux
Classifier: Programming Language :: Python :: 3
Classifier: Programming Language :: Python :: 3.11
Classifier: Programming Language :: Python :: 3.12
Classifier: Programming Language :: Python :: 3.13
Classifier: Programming Language :: Python :: Implementation :: CPython
Classifier: Topic :: Software Development :: Quality Assurance
Classifier: Topic :: Software Development :: Testing
Classifier: Topic :: System :: Hardware :: Universal Serial Bus (USB)
Classifier: Topic :: Utilities
Classifier: Typing :: Typed
Requires-Python: >=3.11
Requires-Dist: lxml>=6.0.2
Requires-Dist: pandas>=3.0.0
Requires-Dist: rich>=13.0.0
Requires-Dist: typer[all]>=0.12.0
Provides-Extra: dev
Requires-Dist: black>=23.0.0; extra == 'dev'
Requires-Dist: commitizen; extra == 'dev'
Requires-Dist: hypothesis>=6.82.0; extra == 'dev'
Requires-Dist: mypy>=1.7.0; extra == 'dev'
Requires-Dist: pytest-cov>=4.1.0; extra == 'dev'
Requires-Dist: pytest-mock>=3.11.0; extra == 'dev'
Requires-Dist: pytest>=7.4.0; extra == 'dev'
Requires-Dist: ruff>=0.1.0; extra == 'dev'
Requires-Dist: syrupy>=4.0.0; extra == 'dev'
Provides-Extra: test
Requires-Dist: hypothesis>=6.82.0; extra == 'test'
Requires-Dist: pytest-cov>=4.1.0; extra == 'test'
Requires-Dist: pytest-mock>=3.11.0; extra == 'test'
Requires-Dist: pytest>=7.4.0; extra == 'test'
Requires-Dist: syrupy>=4.0.0; extra == 'test'
